simpleinject/__init__.py
simpleinject/service_provider.py
simpleinject-1.0.0.dist-info/LICENSE
simpleinject-1.0.0.dist-info/METADATA
simpleinject-1.0.0.dist-info/WHEEL
simpleinject-1.0.0.dist-info/top_level.txt
simpleinject-1.0.0.dist-info/RECORD
