Metadata-Version: 2.1
Name: simpleinject
Version: 1.0.0
Summary: A simple service provider for Python using service injection.
Home-page: https://github.com/Steguer/SimpleInject
Author: Steven Gerard
License: UNKNOWN
Platform: UNKNOWN
Classifier: Programming Language :: Python :: 3
Classifier: License :: OSI Approved :: MIT License
Classifier: Operating System :: OS Independent
